{
  "template": {
    "prefix": "template",
    "body": ["<template>", "\t$0", "</template>"],
    "description": "template element"
  },
  "script": {
    "prefix": "script",
    "body": ["<script>", "$0", "</script>"],
    "description": "script element"
  },
  "script lang": {
    "prefix": "scriptLang",
    "body": ["<script lang=\"${1:ts}\">", "$0", "</script>"],
    "description": "script element with lang"
  },
  "script setup": {
    "prefix": "scriptSetup",
    "body": ["<script setup>", "$0", "</script>"],
    "description": "script setup element"
  },
  "script setup lang": {
    "prefix": "scriptSetupLang",
    "body": ["<script setup lang=\"${1:ts}\">", "$0", "</script>"],
    "description": "script setup element with lang"
  },
  "style": {
    "prefix": "style",
    "body": ["<style>", "$0", "</style>"],
    "description": "style element"
  },
  "style lang": {
    "prefix": "styleLang",
    "body": ["<style lang=\"${1:css}\">", "$0", "</style>"],
    "description": "style element with lang"
  },
  "style scoped": {
    "prefix": "styleScoped",
    "body": ["<style scoped>", "$0", "</style>"],
    "description": "style scoped element"
  },
  "style lang scoped": {
    "prefix": "styleLangScoped",
    "body": ["<style lang=\"$1\" scoped>", "$0", "</style>"],
    "description": "style scoped element with lang"
  },
  "SFC": {
    "prefix": "sfc",
    "body": [
      "<script>",
      "$0",
      "</script>",
      "",
      "<template>",
      "",
      "</template>",
      "",
      "<style scoped>",
      "",
      "</style>"
    ],
    "description": "Single File Component"
  },
  "SFC with lang": {
    "prefix": "sfcLang",
    "body": [
      "<script lang=\"${1:ts}\">",
      "$0",
      "</script>",
      "",
      "<template>",
      "",
      "</template>",
      "",
      "<style scoped>",
      "",
      "</style>"
    ],
    "description": "Single File Component with Lang"
  },
  "SFC setup": {
    "prefix": "sfcSetup",
    "body": [
      "<script setup>",
      "$0",
      "</script>",
      "",
      "<template>",
      "",
      "</template>",
      "",
      "<style scoped>",
      "",
      "</style>"
    ],
    "description": "Single File Component with Setup"
  },
  "SFC setup with lang": {
    "prefix": "sfcSetupLang",
    "body": [
      "<script setup lang=\"${1:ts}\">",
      "$0",
      "</script>",
      "",
      "<template>",
      "",
      "</template>",
      "",
      "<style scoped>",
      "",
      "</style>"
    ],
    "description": "Single File Component with Setup and Lang"
  }
}
